[
  {
    "section": "PewPewCubes",
    "titles": [
      {
        "title": "Graphics Design",
        "names": [
          "Kevin Janzen aka ZaboKev aka K e v",
          "Timon Maier aka _Timon aka Dr. Diarrhö"
        ]
      },
      {
        "title": "Programming",
        "names": [
          "Étienne Muser aka Der_fbs aka fibs"
        ]
      },
      {
        "title": "Audio",
        "names": [
          "ValliHalli"
        ]
      },
      {
        "title": "Map building",
        "names": [
          "Étienne Muser aka Der_fbs aka fibs",
          "Robert Senin aka Sogeking_1024",
          "Aaron Werner aka Sol Astrum"
        ]
      },
      {
        "title": "Alpha testing",
        "names": [
          "Anton Kesy",
          "Philipp Schmidt aka Yochyo",
          "Robert Senin aka Sogeking_1024",
          "ValliHalli",
          "Kevin Janzen aka ZaboKev aka K e v",
          "Étienne Muser aka Der_fbs aka fibs"
        ]
      },
      {
        "title": "Beta testing",
        "names": [
          "Étienne Muser aka Der_fbs aka fibs"
        ]
      },
      {
        "title": "Post credits text",
        "names": [
          "Aaron Werner aka Sol Astrum"
        ]
      },
      {
        "title": "Powered by",
        "names": [
          "GeckoLib     MIT license",
          "Fabric API   Apache-2.0 license"
        ]
      }
    ]
  }
]